{"annotation":"","encodeName":"shaizi_anmi7","ext":"png","folders":["ba39ce87-ef5d-0ae2-c7ef-8c4d81a397cd"],"height":500,"id":"495975da-5061-a85f-8c96-22b1e8e91bb5","isDeleted":false,"modificationTime":1524622178400,"name":"shaizi_anmi7","palettes":[{"color":[228,227,211],"ratio":86.82028233208837},{"color":[15,42,133],"ratio":8.856111919984807},{"color":[170,8,13],"ratio":2.911945306070773},{"color":[148,150,157],"ratio":1.0571627524213458},{"color":[140,124,108],"ratio":0.3544976894347028}],"size":10470,"tags":["麻将"],"url":"","width":500}