{"annotation":"","encodeName":"shaizi_anmi5","ext":"png","folders":["3395e4bc-7a01-f422-517c-b5f52ad9d42d"],"height":140,"id":"1328a637-af4a-65c0-89a9-d4be0f709bd7","isDeleted":false,"modificationTime":1524541055895,"name":"shaizi_anmi5","palettes":[{"color":[220,219,203],"ratio":87.05157813702849},{"color":[28,43,131],"ratio":7.051578137028483},{"color":[160,13,15],"ratio":4.095458044649731},{"color":[141,147,166],"ratio":1.447267128560431},{"color":[156,108,100],"ratio":0.3541185527328714}],"size":3849,"tags":["麻将"],"url":"","width":190}