{"annotation":"","encodeName":"specialFish3Swim","ext":"png","folders":["ba39ce87-ef5d-0ae2-c7ef-8c4d81a397cd"],"height":256,"id":"0a6a3ba3-192c-29ab-4def-25b6364b4707","isDeleted":false,"modificationTime":1524622120135,"name":"specialFish3Swim","palettes":[{"color":[134,79,39],"ratio":55.91976293594711},{"color":[242,216,47],"ratio":19.945292910873032},{"color":[213,152,48],"ratio":9.409619329838158},{"color":[57,34,17],"ratio":3.8294962388876224},{"color":[182,143,33],"ratio":10.895828584454069}],"size":91936,"tags":["捕鱼的鱼"],"url":"","width":512}