{"annotation":"","encodeName":"050%E8%85%BE%E8%AE%AF%E6%B8%B8%E6%88%8F%E6%AC%A2%E4%B9%90%E6%8B%BC%E4%B8%89%E5%BC%A0%E7%82%B8%E9%87%91%E8%8A%B1%E6%A3%8B%E7%89%8C%E6%B8%B8%E6%88%8FUI%E7%95%8C%E9%9D%A2%E7%BE%8E%E6%9C%AF%E8%B5%84%E6%BA%90%E6%B7%98%E5%AE%9D%E7%BD%91","ext":"png","folders":["3395e4bc-7a01-f422-517c-b5f52ad9d42d"],"height":512,"id":"6e3fe6e9-8b0e-456f-f57e-9b259e777c8a","isDeleted":false,"modificationTime":1525398520005,"name":"050腾讯游戏欢乐拼三张炸金花棋牌游戏UI界面美术资源淘宝网","palettes":[{"$$hashKey":"object:20046","color":[38,25,46],"ratio":91.77932739257812},{"$$hashKey":"object:20048","color":[170,108,116],"ratio":1.4453887939453125},{"$$hashKey":"object:20047","color":[104,64,82],"ratio":4.4712066650390625},{"$$hashKey":"object:20050","color":[70,138,111],"ratio":1.01470947265625},{"$$hashKey":"object:20049","color":[89,70,125],"ratio":1.28936767578125}],"size":264587,"tags":["背景"],"url":"https://item.taobao.com/item.htm?spm=a230r.1.14.275.nxu13e&id=533637146179&ns=1&abbucket=10#detail","width":512}