{"annotation":"","encodeName":"bg_4jpg%20(1920%C3%97960)","ext":"jpg","folders":["0b0b7e16-67b2-c4f4-438a-7a3db6d6281c"],"height":960,"id":"0627b292-5360-1534-f52a-87821b7471c4","isDeleted":false,"modificationTime":1524554285216,"name":"bg_4jpg (1920×960)","palettes":[{"$$hashKey":"object:51513","color":[129,222,232],"ratio":58.62109375},{"$$hashKey":"object:51516","color":[46,82,143],"ratio":7.96826171875},{"$$hashKey":"object:51515","color":[220,224,185],"ratio":8.30322265625},{"$$hashKey":"object:51514","color":[30,148,203],"ratio":21.91796875},{"$$hashKey":"object:51517","color":[129,151,51],"ratio":3.1894531249999996}],"size":275789,"tags":["背景"],"url":"http://happyfish.lkgame.com/img/bg_4.jpg","width":1920}