{"annotation":"","encodeName":"shaizi_anmi6","ext":"png","folders":["3395e4bc-7a01-f422-517c-b5f52ad9d42d"],"height":140,"id":"461844b9-e52e-6cfe-ea7b-40672c07af66","isDeleted":false,"modificationTime":1524541055894,"name":"shaizi_anmi6","palettes":[{"color":[223,223,206],"ratio":85.2467024914509},{"color":[18,42,135],"ratio":6.66015306953265},{"color":[173,19,21],"ratio":5.911089399120664},{"color":[138,144,158],"ratio":1.7261032405145742},{"color":[164,124,108],"ratio":0.4559517993812083}],"size":3911,"tags":["麻将"],"url":"","width":190}