{"annotation":"","encodeName":"%E5%A3%81%E7%BA%B8","ext":"jpg","folders":["0b0b7e16-67b2-c4f4-438a-7a3db6d6281c"],"height":1080,"id":"79d072ab-55cb-d9e4-8171-15dd3c29255a","isDeleted":false,"modificationTime":1524554285163,"name":"壁纸","palettes":[{"$$hashKey":"object:52595","color":[57,188,222],"ratio":57.380208333333336},{"$$hashKey":"object:52596","color":[204,216,213],"ratio":22.294270833333332},{"$$hashKey":"object:52598","color":[43,56,122],"ratio":5.336805555555555},{"$$hashKey":"object:52597","color":[24,109,194],"ratio":13.07638888888889},{"$$hashKey":"object:52599","color":[80,110,94],"ratio":1.9123263888888888}],"size":1657764,"tags":["背景"],"url":"http://huaban.com/boards/29061425/","width":1920}