{"annotation":"","encodeName":"bg_hubei","ext":"png","folders":["3395e4bc-7a01-f422-517c-b5f52ad9d42d"],"height":1024,"id":"7dc50825-f82e-de81-9075-8ae85c1502ac","isDeleted":false,"modificationTime":1525398721321,"name":"bg_hubei","palettes":[{"color":[84,75,74],"ratio":59.883544921875},{"color":[200,199,163],"ratio":16.839111328125},{"color":[100,144,213],"ratio":9.078857421875},{"color":[191,148,106],"ratio":6.1318359375},{"color":[152,143,113],"ratio":8.066650390625}],"size":725778,"tags":["场景"],"url":"http://huaban.com/boards/38514648/","width":1024}