{"annotation":"","encodeName":"%E5%8E%9F%E5%88%9B%E4%BD%9C%E5%93%81%EF%BC%9A%E5%8F%A3%E8%A2%8B%E6%8D%95%E9%B1%BC","ext":"png","folders":["0b0b7e16-67b2-c4f4-438a-7a3db6d6281c"],"height":1133,"id":"02854eca-c63c-316c-7b1d-1b7266d68ca8","isDeleted":false,"modificationTime":1524554285077,"name":"原创作品：口袋捕鱼","palettes":[{"$$hashKey":"object:55016","color":[25,96,101],"ratio":72.9114420062696},{"$$hashKey":"object:55018","color":[196,146,109],"ratio":8.898902821316614},{"$$hashKey":"object:55017","color":[85,198,178],"ratio":10.143025078369906},{"$$hashKey":"object:55019","color":[23,31,47],"ratio":6.6763812695924765},{"$$hashKey":"object:55020","color":[63,124,207],"ratio":1.3702488244514108}],"size":2101761,"tags":["捕鱼炮台"],"url":"http://www.zcool.com.cn/work/ZMjE1NDY2NjQ=/2.html","width":1136}