{"annotation":"","encodeName":"bg_hebei","ext":"png","folders":["3395e4bc-7a01-f422-517c-b5f52ad9d42d"],"height":1024,"id":"503c88fe-fcb3-bf71-789b-e0316c23ee40","isDeleted":false,"modificationTime":1525398721320,"name":"bg_hebei","palettes":[{"color":[164,123,103],"ratio":85.92529296875},{"color":[70,46,51],"ratio":7.837646484374999},{"color":[241,214,149],"ratio":3.4655761718749996},{"color":[105,45,38],"ratio":2.135498046875},{"color":[158,132,198],"ratio":0.635986328125}],"size":786899,"tags":["场景"],"url":"http://huaban.com/boards/38514648/","width":1024}