{"annotation":"","encodeName":"CommonBlackJack","ext":"png","folders":["3395e4bc-7a01-f422-517c-b5f52ad9d42d"],"height":1024,"id":"06c744d3-2e39-3b94-8018-5b7321e0acf2","isDeleted":false,"modificationTime":1524540959333,"name":"CommonBlackJack","palettes":[{"color":[79,75,146],"ratio":50.80047070414055},{"color":[223,170,138],"ratio":17.798272260383314},{"color":[142,191,210],"ratio":6.621785574195196},{"color":[157,109,183],"ratio":14.93390985468378},{"color":[58,70,57],"ratio":9.845561606597157}],"size":4198755,"tags":["棋牌多个素材"],"url":"","width":1024}