{"annotation":"","encodeName":"final_table","ext":"png","folders":["3395e4bc-7a01-f422-517c-b5f52ad9d42d"],"height":513,"id":"1454b620-a7d5-6124-0fb0-f9efbf94bf95","isDeleted":false,"modificationTime":1525398721233,"name":"final_table","palettes":[{"color":[161,122,69],"ratio":92.76247642824892},{"color":[233,208,138],"ratio":1.3306419484210246},{"color":[107,71,33],"ratio":4.9236408063530845},{"color":[204,177,118],"ratio":0.7776685878197126},{"color":[196,172,124],"ratio":0.2055722291572601}],"size":110326,"tags":["桌面"],"url":"http://huaban.com/boards/38514648/","width":573}