{"annotation":"","encodeName":"38","ext":"png","folders":["ba39ce87-ef5d-0ae2-c7ef-8c4d81a397cd"],"height":73,"id":"fa10bd12-fce6-00a7-7882-8e30a96a16a5","isDeleted":false,"modificationTime":1524622144682,"name":"38","palettes":[{"color":[163,4,4],"ratio":24.169184290030213},{"color":[6,13,48],"ratio":57.70392749244713},{"color":[79,4,12],"ratio":6.797583081570997},{"color":[42,5,39],"ratio":9.667673716012084},{"color":[52,4,4],"ratio":1.6616314199395772}],"size":2123,"tags":["麻将"],"url":"","width":53}